rustypdf-0.1.1.dist-info/METADATA
rustypdf-0.1.1.dist-info/WHEEL
rustypdf-0.1.1.dist-info/entry_points.txt
rustypdf-0.1.1.dist-info/license_files/LICENSE
_rustypdf/__init__.py
_rustypdf/_rustypdf.cpython-312-darwin.so
rustypdf-0.1.1.dist-info/RECORD
