Metadata-Version: 2.3
Name: rustypdf
Version: 0.1.1
Classifier: Programming Language :: Python
Classifier: Programming Language :: Python :: 3
Classifier: Programming Language :: Rust
Classifier: License :: OSI Approved :: MIT License
Classifier: Operating System :: OS Independent
Requires-Dist: pypdf >=4, <5
License-File: LICENSE
Summary: CLI tool to compress and merge PDFs (Rust backend via PyO3)
Keywords: pdf,compression,merge,cli,rust,pyo3,rustypdf
Author: Shyam Sundar <rampallishyam2@gmail.com>
Author-email: Shyam Sundar <rampallishyam2@gmail.com>
License: MIT
Requires-Python: >=3.8
Project-URL: Homepage, https://example.com
Project-URL: Repository, https://example.com/repo
